Metadata-Version: 2.1
Name: scidx
Version: 0.4.1
Summary: Python client library for interacting with the sciDX API
Home-page: https://github.com/sci-ndp/scidx-py
Author: Raul Bardaji, Saleem Alharir, Andreu Fornos, Philip Davis, Ivan Rodero, Manish Parashar
Author-email: rbardaji@gmail.com, saleem.alharir@utah.edu, andreu.fornos@utah.edu, philip.e.davis@utah.edu, ivan.rodero@utah.edu, manish.parashar@utah.edu
License: UNKNOWN
Platform: UNKNOWN
Classifier: Programming Language :: Python :: 3
Classifier: License :: OSI Approved :: MIT License
Classifier: Operating System :: OS Independent
Requires-Python: >=3.6
License-File: LICENSE
License-File: AUTHORS
Requires-Dist: aiokafka
Requires-Dist: pytest
Requires-Dist: pytest-asyncio
Requires-Dist: pytest-env
Requires-Dist: pytest-order
Requires-Dist: python-dateutil
Requires-Dist: requests
Provides-Extra: staging
Requires-Dist: dxspaces >=0.0.6 ; extra == 'staging'
Requires-Dist: numpy ; extra == 'staging'
